pygooglenews/__init__.py
pygooglenews-0.1.1.dist-info/LICENSE
pygooglenews-0.1.1.dist-info/WHEEL
pygooglenews-0.1.1.dist-info/METADATA
pygooglenews-0.1.1.dist-info/RECORD
